yahoo_search/__init__.py
yahoo_search/core.py
yahoosearcher_py-0.0.1.dist-info/METADATA
yahoosearcher_py-0.0.1.dist-info/WHEEL
yahoosearcher_py-0.0.1.dist-info/top_level.txt
yahoosearcher_py-0.0.1.dist-info/RECORD
